django_fakery/__init__.py
django_fakery/blueprint.py
django_fakery/compat.py
django_fakery/exceptions.py
django_fakery/faker_factory.py
django_fakery/fakes.py
django_fakery/field_mappings.py
django_fakery/lazy.py
django_fakery/plugin.py
django_fakery/py.typed
django_fakery/rels.py
django_fakery/shortcuts.py
django_fakery/types.py
django_fakery/utils.py
django_fakery/values.py
django_fakery-4.1.3.dist-info/LICENSE
django_fakery-4.1.3.dist-info/METADATA
django_fakery-4.1.3.dist-info/WHEEL
django_fakery-4.1.3.dist-info/entry_points.txt
django_fakery-4.1.3.dist-info/top_level.txt
django_fakery-4.1.3.dist-info/RECORD
