Metadata-Version: 2.1
Name: django-fakery
Version: 4.1.3
Summary: A model instances generator for Django
Home-page: https://github.com/fcurella/django-fakery/
Author: Flavio Curella
Author-email: flavio.curella@gmail.com
License: MIT
Platform: any
Classifier: Development Status :: 4 - Beta
Classifier: Framework :: Django
Classifier: License :: OSI Approved :: MIT License
Classifier: Operating System :: OS Independent
Classifier: Programming Language :: Python
Classifier: Programming Language :: Python :: 3
Classifier: Programming Language :: Python :: 3.8
Classifier: Programming Language :: Python :: 3.9
Classifier: Programming Language :: Python :: 3.10
Classifier: Programming Language :: Python :: 3.11
Requires-Python: >=3.8
License-File: LICENSE
Requires-Dist: Faker <11.0,>=10.0
Requires-Dist: Django >=3.2
Requires-Dist: six >=1.10.1
